{
  "updated": "2026-03-28T14:27:33.352418+00:00",
  "locations": [
    {
      "name": "Mesa, AZ",
      "zip": "85208",
      "label": "local",
      "current": {
        "temperature_f": 68,
        "wind_speed": "15 mph",
        "wind_direction": "E",
        "short_forecast": "Partly Sunny",
        "is_daytime": true
      },
      "periods": [
        {
          "name": "Today",
          "temperature_f": 95,
          "short_forecast": "Mostly Sunny",
          "wind_speed": "5 to 15 mph",
          "wind_direction": "E",
          "is_daytime": true
        },
        {
          "name": "Tonight",
          "temperature_f": 68,
          "short_forecast": "Partly Cloudy",
          "wind_speed": "5 mph",
          "wind_direction": "E",
          "is_daytime": false
        },
        {
          "name": "Sunday",
          "temperature_f": 97,
          "short_forecast": "Mostly Sunny",
          "wind_speed": "0 to 5 mph",
          "wind_direction": "S",
          "is_daytime": true
        },
        {
          "name": "Sunday Night",
          "temperature_f": 71,
          "short_forecast": "Mostly Cloudy",
          "wind_speed": "0 to 5 mph",
          "wind_direction": "SE",
          "is_daytime": false
        },
        {
          "name": "Monday",
          "temperature_f": 95,
          "short_forecast": "Sunny",
          "wind_speed": "0 to 5 mph",
          "wind_direction": "S",
          "is_daytime": true
        },
        {
          "name": "Monday Night",
          "temperature_f": 68,
          "short_forecast": "Mostly Cloudy",
          "wind_speed": "0 to 5 mph",
          "wind_direction": "SSW",
          "is_daytime": false
        }
      ],
      "error": null
    }
  ]
}